py_build/__init__.py
py_build/build_file.py
hc_py_build-0.0.1.dist-info/METADATA
hc_py_build-0.0.1.dist-info/WHEEL
hc_py_build-0.0.1.dist-info/top_level.txt
hc_py_build-0.0.1.dist-info/RECORD
